<?xml version='1.0' encoding='UTF-8'?>
<!DOCTYPE beans PUBLIC '-//SPRING//DTD BEAN//EN' 'http://www.springframework.org/dtd/spring-beans.dtd'>
<beans>
    <!-- Add Someco Workflow messages -->
    <bean id="mvn-tutorial-share_resources" class="org.springframework.extensions.surf.util.ResourceBundleBootstrapComponent">
        <property name="resourceBundles">
            <list>
                <value>alfresco.web-extension.module.${project.artifactId}.messages.autoDealWorkflow_en</value>
                <value>alfresco.web-extension.module.${project.artifactId}.messages.autoDealWorkflow_ru</value>
            </list>
        </property>
    </bean>
</beans>